pytest_agents/__init__.py
pytest_agents/agent_bridge.py
pytest_agents/cli.py
pytest_agents/config.py
pytest_agents/fixtures.py
pytest_agents/hooks.py
pytest_agents/markers.py
pytest_agents/metrics_server.py
pytest_agents/plugin.py
pytest_agents/py.typed
pytest_agents/di/__init__.py
pytest_agents/di/container.py
pytest_agents/infrastructure/__init__.py
pytest_agents/infrastructure/env_config_factory.py
pytest_agents/infrastructure/prometheus_metrics.py
pytest_agents/infrastructure/subprocess_runner.py
pytest_agents/interfaces/__init__.py
pytest_agents/interfaces/core.py
pytest_agents/utils/__init__.py
pytest_agents/utils/logging.py
pytest_agents/utils/validation.py
pytest_agents-1.0.15.dist-info/METADATA
pytest_agents-1.0.15.dist-info/WHEEL
pytest_agents-1.0.15.dist-info/entry_points.txt
pytest_agents-1.0.15.dist-info/RECORD
