Metadata-Version: 2.4
Name: pytest-agents
Version: 1.0.15
Summary: Pytest plugin framework with AI agent capabilities for multi-agent testing
Author-email: Kevin McAllorum <kmcallorum@example.com>
License: MIT
Keywords: agents,ai,multi-agent,pytest,testing,typescript
Classifier: Development Status :: 3 - Alpha
Classifier: Framework :: Pytest
Classifier: Intended Audience :: Developers
Classifier: License :: OSI Approved :: MIT License
Classifier: Programming Language :: Python :: 3.11
Classifier: Programming Language :: Python :: 3.12
Classifier: Topic :: Software Development :: Testing
Requires-Python: >=3.11
Requires-Dist: dependency-injector>=4.41.0
Requires-Dist: prometheus-client>=0.19.0
Requires-Dist: pytest>=8.0.0
Requires-Dist: typing-extensions>=4.9.0
Provides-Extra: dev
Requires-Dist: mypy>=1.8.0; extra == 'dev'
Requires-Dist: pytest-benchmark>=4.0.0; extra == 'dev'
Requires-Dist: pytest-cov>=4.1.0; extra == 'dev'
Requires-Dist: ruff>=0.1.0; extra == 'dev'
